rp4/__init__.py
rp4/__main__.py
rp4/cli.py
rp4/client.py
rp4/desktop_shortcut.py
rp4/gui.py
rp4/defaults/global_settings.json
rp4/defaults/preset_settings.json
rp4-0.0.3.dist-info/LICENSE
rp4-0.0.3.dist-info/METADATA
rp4-0.0.3.dist-info/WHEEL
rp4-0.0.3.dist-info/entry_points.txt
rp4-0.0.3.dist-info/top_level.txt
rp4-0.0.3.dist-info/RECORD
