Metadata-Version: 2.1
Name: rp4
Version: 0.0.3
Summary: Simple python replacement for the bloated LLM frontends.
Author: Ren Tatsumoto, asakura42
License: GPL-3
Classifier: Programming Language :: Python :: 3
Requires-Python: >=3.10
License-File: LICENSE
Requires-Dist: g4f
Requires-Dist: requests
Requires-Dist: markdown2
Requires-Dist: pyqt6
